TerminalCharacterSheet/__init__.py
TerminalCharacterSheet/character_sheet.py
TerminalCharacterSheet/logger.py
TerminalCharacterSheet/sheet_variables.py
TerminalCharacterSheet/modules/acrobatics/module.art
TerminalCharacterSheet/modules/acrobatics/module.info
TerminalCharacterSheet/modules/animal_handling/module.art
TerminalCharacterSheet/modules/animal_handling/module.info
TerminalCharacterSheet/modules/arcana/module.art
TerminalCharacterSheet/modules/arcana/module.info
TerminalCharacterSheet/modules/armour_class/module.art
TerminalCharacterSheet/modules/armour_class/module.info
TerminalCharacterSheet/modules/athletics/module.art
TerminalCharacterSheet/modules/athletics/module.info
TerminalCharacterSheet/modules/attack_roll/module.art
TerminalCharacterSheet/modules/attack_roll/module.info
TerminalCharacterSheet/modules/banner/module.art
TerminalCharacterSheet/modules/banner/module.info
TerminalCharacterSheet/modules/casting/module.art
TerminalCharacterSheet/modules/casting/module.info
TerminalCharacterSheet/modules/character_name/module.art
TerminalCharacterSheet/modules/character_name/module.info
TerminalCharacterSheet/modules/charisma/module.art
TerminalCharacterSheet/modules/charisma/module.info
TerminalCharacterSheet/modules/charisma_saving_throw/module.art
TerminalCharacterSheet/modules/charisma_saving_throw/module.info
TerminalCharacterSheet/modules/class/module.art
TerminalCharacterSheet/modules/class/module.info
TerminalCharacterSheet/modules/coin_pouch/module.art
TerminalCharacterSheet/modules/coin_pouch/module.info
TerminalCharacterSheet/modules/combat_stats/module.art
TerminalCharacterSheet/modules/combat_stats/module.info
TerminalCharacterSheet/modules/constitution/module.art
TerminalCharacterSheet/modules/constitution/module.info
TerminalCharacterSheet/modules/constitution_saving_throw/module.art
TerminalCharacterSheet/modules/constitution_saving_throw/module.info
TerminalCharacterSheet/modules/deception/module.art
terminal_character_sheet-0.1.1rc0.dist-info/LICENSE
terminal_character_sheet-0.1.1rc0.dist-info/METADATA
terminal_character_sheet-0.1.1rc0.dist-info/WHEEL
terminal_character_sheet-0.1.1rc0.dist-info/top_level.txt
terminal_character_sheet-0.1.1rc0.dist-info/RECORD
