Metadata-Version: 2.1
Name: terminal-character-sheet
Version: 0.1.1rc0
Summary: Programmable ASCII Character Sheet
Author-email: Frankie Homewood <F.Homewood@outlook.com>
License: 
Project-URL: Homepage, https://github.com/FHomewood/Terminal-Character-Sheet
Project-URL: Bug Tracker, https://github.com/FHomewood/Terminal-Character-Sheet/issues
Classifier: Programming Language :: Python :: 3
Classifier: License :: OSI Approved :: Apache Software License
Classifier: Operating System :: OS Independent
Requires-Python: >=3.7
License-File: LICENSE
